mmgpt/__init__.py
mmgpt/datasets/__init__.py
mmgpt/datasets/alpaca_gpt4_dataset.py
mmgpt/datasets/aokvqa_dataset.py
mmgpt/datasets/builder.py
mmgpt/datasets/cc_sbu_align_dataset.py
mmgpt/datasets/clevr_dataset.py
mmgpt/datasets/coco_caption_dataset.py
mmgpt/datasets/dial_dataset.py
mmgpt/datasets/dolly_dataset.py
mmgpt/datasets/gqa_dataset.py
mmgpt/datasets/llava_dataset.py
mmgpt/datasets/nlvr_dataset.py
mmgpt/datasets/ocr_vqa_dataset.py
mmgpt/datasets/snli_ve_datasets.py
mmgpt/datasets/text_ocr_dataset.py
mmgpt/datasets/vqa_dataset.py
mmgpt/datasets/samplers/__init__.py
mmgpt/datasets/samplers/infinite_sampler.py
mmgpt/models/__init__.py
mmgpt/models/builder.py
mmgpt/models/blip2/__init__.py
mmgpt/models/open_flamingo/__init__.py
mmgpt/models/open_flamingo/builder.py
mmgpt/models/open_flamingo/flamingo.py
mmgpt/models/open_flamingo/flamingo_lm.py
mmgpt/models/open_flamingo/helpers.py
mmgpt/models/open_flamingo/utils.py
mmgpt/train/__init__.py
mmgpt/train/distributed.py
mmgpt/train/instruction_finetune.py
mmgpt/train/train_utils.py
mmgpt-0.0.1.data/data/README.md
mmgpt-0.0.1.dist-info/LICENSE
mmgpt-0.0.1.dist-info/METADATA
mmgpt-0.0.1.dist-info/WHEEL
mmgpt-0.0.1.dist-info/top_level.txt
mmgpt-0.0.1.dist-info/RECORD
