Metadata-Version: 2.1
Name: mmgpt
Version: 0.0.1
Summary: An open-source framework for multi-modality instruction fine-tuning
License: Apache 2.0
Keywords: machine learning
License-File: LICENSE
Requires-Dist: einops
Requires-Dist: einops-exts
Requires-Dist: transformers
Requires-Dist: torch
Requires-Dist: torchvision
Requires-Dist: pillow
Requires-Dist: more-itertools
Requires-Dist: datasets
Requires-Dist: braceexpand
Requires-Dist: webdataset
Requires-Dist: wandb
Requires-Dist: nltk
Requires-Dist: scipy
Requires-Dist: inflection
Requires-Dist: sentencepiece
Requires-Dist: open-clip-torch
